{
  "swagger": "2.0",
  "info": {
    "version": "1.0.0",
    "title": "Shopping App - CRUD",
    "description": "My Shopping App Project Application API",
    "license": {
      "name": "MIT",
      "url": "https://opensource.org/licenses/MIT"
    }
  },
  "host": "localhost:4000",
  "basePath": "/",
  "tags": [
    {
      "name": "Categories",
      "description": "Categories API"
    }
  ],
  "schemes": [
    "http"
  ],
  "consumes": [
    "application/json"
  ],
  "produces": [
    "application/json"
  ],
  "paths": {
    "/api/category": {
      "get": {
        "tags": [
          "Categories"
        ],
        "summary": "Get all categories",
        "parameters": [
          {
            "name": "categoryName",
            "in": "query",
            "required": false,
            "description": "Category Name",
            "type": "string"
          }
        ],
        "responses": {
          "200": {
            "description": "OK",
            "schema": {
              "$ref": "#/definitions/ServiceResponse"
            }
          }
        }
      },
      "post": {
        "tags": [
          "Categories"
        ],
        "summary": "Create Category API",
        "parameters": [
          {
            "name": "categoryName",
            "in": "formData",
            "description": "Category Name",
            "required": true,
            "type": "string"
          },
          {
            "name": "categoryDescription",
            "in": "formData",
            "description": "Category Description",
            "type": "string"
          },
          {
            "name": "categoryImage",
            "in": "formData",
            "description": "Category Image",
            "type": "file"
          }
        ],
        "responses": {
          "200": {
            "description": "OK",
            "schema": {
              "$ref": "#/definitions/ServiceResponse"
            }
          }
        }
      }
    },
    "/api/category/{id}": {
      "parameters": [
        {
          "name": "id",
          "in": "path",
          "required": true,
          "description": "Category Id",
          "type": "string"
        }
      ],
      "get": {
        "tags": [
          "Categories"
        ],
        "summary": "Category Details based on Category Id",
        "responses": {
          "200": {
            "description": "OK",
            "schema": {
              "$ref": "#/definitions/ServiceResponse"
            }
          }
        }
      },
      "put": {
        "tags": [
          "Categories"
        ],
        "summary": "Update Category API",
        "parameters": [
          {
            "name": "categoryName",
            "in": "formData",
            "description": "Category Name",
            "required": true,
            "type": "string"
          },
          {
            "name": "categoryDescription",
            "in": "formData",
            "description": "Category Description",
            "type": "string"
          },
          {
            "name": "categoryImage",
            "in": "formData",
            "description": "Category Image",
            "type": "file"
          }
        ],
        "responses": {
          "200": {
            "description": "OK",
            "schema": {
              "$ref": "#/definitions/ServiceResponse"
            }
          }
        }
      },
      "delete": {
        "tags": [
          "Categories"
        ],
        "summary": "Delete Category API",
        "responses": {
          "200": {
            "description": "OK",
            "schema": {
              "$ref": "#/definitions/ServiceResponse"
            }
          }
        }
      }
    }
  },
  "definitions": {
    "Category": {
      "required": [
        "categoryName",
        "_id"
      ],
      "properties": {
        "_id": {
          "type": "string",
          "uniqueItems": true
        },
        "categoryName": {
          "type": "string"
        },
        "categoryDescription": {
          "type": "string"
        },
        "categoryImage": {
          "type": "string"
        }
      }
    },
    "ServiceResponse": {
      "properties": {
        "message": {
          "type": "string"
        },
        "data": {
          "type": "array",
          "items": {
            "$ref": "#/definitions/Category"
          }
        }
      }
    }
  }
}